psat_api/common/AssignmentStatus.py
psat_api/common/EnrollmentStatus.py
psat_api/common/Region.py
psat_api/common/Version.py
psat_api/common/__init__.py
psat_api/v3/Client.py
psat_api/v3/__init__.py
psat_api/v3/filters/CyberStrengthFilter.py
psat_api/v3/filters/EnrollmentsFilter.py
psat_api/v3/filters/PhishAlarmFilter.py
psat_api/v3/filters/PhishingExtendedFilter.py
psat_api/v3/filters/PhishingFilter.py
psat_api/v3/filters/TrainingFilter.py
psat_api/v3/filters/UsersFilter.py
psat_api/v3/filters/__init__.py
psat_api/v3/reports/CyberStrength.py
psat_api/v3/reports/Enrollments.py
psat_api/v3/reports/PhishAlarm.py
psat_api/v3/reports/Phishing.py
psat_api/v3/reports/PhishingExtended.py
psat_api/v3/reports/Reports.py
psat_api/v3/reports/Training.py
psat_api/v3/reports/Users.py
psat_api/v3/reports/__init__.py
psat_api/web/ClientBase.py
psat_api/web/ClientGeneric.py
psat_api/web/ErrorHandler.py
psat_api/web/FilterOptions.py
psat_api/web/PageIterator.py
psat_api/web/Resource.py
psat_api/web/__init__.py
psat_api-3.1.0.dist-info/LICENSE
psat_api-3.1.0.dist-info/METADATA
psat_api-3.1.0.dist-info/WHEEL
psat_api-3.1.0.dist-info/top_level.txt
psat_api-3.1.0.dist-info/RECORD
