Metadata-Version: 2.1
Name: psat-api
Version: 3.1.0
Summary: Proofpoint Security Awareness Training Python API Package
License: MIT
Project-URL: repository, https://github.com/pfptcommunity/psat-api-python
Project-URL: homepage, https://www.proofpoint.com/us/products/security-awareness-training
Project-URL: documentation, https://proofpoint.securityeducation.com/api/reporting/documentation
Requires-Python: >3.9
License-File: LICENSE
Requires-Dist: requests
Requires-Dist: pysocks
